ChatAIStream.py
__init__.py
chatai_stream-1.0.2.dist-info/LICENSE
chatai_stream-1.0.2.dist-info/METADATA
chatai_stream-1.0.2.dist-info/WHEEL
chatai_stream-1.0.2.dist-info/top_level.txt
chatai_stream-1.0.2.dist-info/RECORD
