Metadata-Version: 2.1
Name: chatai-stream
Version: 1.0.2
Summary: ChatGPT reacts YouTube chat messages.
Home-page: https://github.com/GeneralYadoc/ChatAIStream
Author: General Yadoc
Author-email: 133023047+GeneralYadoc@users.noreply.github.com
License: MIT
Platform: UNKNOWN
Classifier: Development Status :: 4 - Beta
Classifier: Programming Language :: Python
Classifier: Programming Language :: Python :: 3.7
Classifier: Programming Language :: Python :: 3.8
Classifier: Programming Language :: Python :: 3.9
Classifier: License :: OSI Approved :: MIT License
License-File: LICENSE
Requires-Dist: chatai-agent (==1.1.2)
Requires-Dist: streamchat-agent (==1.0.2)
